{
    "title": "@fibonacci: Calculando fibonatti",
    "description": "# Calculando fibonatti\n\n![_](https://raw.githubusercontent.com/qxcodefup/arcade/master/base/fibonacci/cover.jpg)\n\n## Motiva\u00e7\u00e3o\n\nPedrinho est\u00e1 no mundo da matem\u00e1tica e agora ele \u00e9 o cara, mas precisa da sua ajuda por hora.\n\nEle est\u00e1 estudando sobre a s\u00e9rie de Fibonacci, para quem n\u00e3o sabe ou quem quer saber, um novo termo na sequ\u00eancia de Fibonacci \u00e9 gerado pela soma dos dois anteriores, come\u00e7ando em 1 e 2, os dez primeiros termos da serie de Fibonacci s\u00e3o:\n\n```py\n1, 2, 3, 5, 8, 13, 21, 34,55, 89, ...\n```\n\nPedrinho quer dado um limite predefinido, calcular a soma de todos os termos da sequencia de fibonacci cujo valor \u00e9 par.\n\n## A\u00e7\u00e3o\n\n- Dado um inteiro N e considerando os termos na sequ\u00eancia de Fibonacci cujos valores n\u00e3o excedem N, encontre a soma dos termos de valor par.\n\n### Entrada\n\n- 1 Inteiro N, 1 \\< N \\< 4000000.\n\n## Saida\n\n- A soma dos termos de valor par\n\n## Exemplos\n\n``` py\n>>>>>>>> INSERT Teste 0\n50\n======== EXPECT\n44\n<<<<<<<< FINISH\n```\n\n```py\n>>>>>>>> INSERT Teste 1\n100\n======== EXPECT\n44\n<<<<<<<< FINISH\n```\n\n```py\n>>>>>>>> INSERT Teste 2\n1000000\n======== EXPECT\n1089154\n<<<<<<<< FINISH\n```\n",
    "upload": [
        {
            "name": "vpl_evaluate.cases",
            "contents": ">>>>>>>> INSERT Teste 0\n50\n======== EXPECT\n44\n<<<<<<<< FINISH\n\n\n>>>>>>>> INSERT Teste 1\n100\n======== EXPECT\n44\n<<<<<<<< FINISH\n\n\n>>>>>>>> INSERT Teste 2\n1000000\n======== EXPECT\n1089154\n<<<<<<<< FINISH\n\n\n>>>>>>>> INSERT Teste 3\n500000\n======== EXPECT\n257114\n<<<<<<<< FINISH\n\n\n>>>>>>>> INSERT Teste 4\n30000\n======== EXPECT\n14328\n<<<<<<<< FINISH\n\n\n>>>>>>>> INSERT Teste 5\n500\n======== EXPECT\n188\n<<<<<<<< FINISH\n\n\n>>>>>>>> INSERT Teste 6\n3000000\n======== EXPECT\n1089154\n<<<<<<<< FINISH\n\n\n>>>>>>>> INSERT Teste 7\n4000000\n======== EXPECT\n4613732\n<<<<<<<< FINISH\n\n",
            "type": "hide"
        }
    ],
    "draft": {}
}
