{
  "title": "@130 $06_mat L2 - Bingo!",
  "description": "<!DOCTYPE html>\n<html xmlns=\"http://www.w3.org/1999/xhtml\" lang=\"\" xml:lang=\"\">\n<head>\n  <meta charset=\"utf-8\" />\n  <meta name=\"generator\" content=\"pandoc\" />\n  <meta name=\"viewport\" content=\"width=device-width, initial-scale=1.0, user-scalable=yes\" />\n  <title>@130 $06_mat L2 - Bingo\\!</title>\n  <style>\n      code{white-space: pre-wrap;}\n      span.smallcaps{font-variant: small-caps;}\n      span.underline{text-decoration: underline;}\n      div.column{display: inline-block; vertical-align: top; width: 50%;}\n  </style>\n  <!--[if lt IE 9]>\n    <script src=\"//cdnjs.cloudflare.com/ajax/libs/html5shiv/3.7.3/html5shiv-printshiv.min.js\"></script>\n  <![endif]-->\n</head>\n<body>\n<h2 id=\"mat-l2---bingo\">$06_mat L2 - Bingo!</h2>\n<h2 id=\"qxcode\"><span class=\"citation\" data-cites=\"qxcode\">@qxcode</span></h2>\n<p><img src=\"https://raw.githubusercontent.com/qxcodefup/arcade/master/base/130/__capa.jpg\" /></p>\n<h2 id=\"motiva\u00e7\u00e3o\">Motiva\u00e7\u00e3o</h2>\n<p>Sua v\u00f3, que \u00e9 uma frenquentadora ass\u00eddua do bingo dos idosos, estava tendo dificuldades para saber quantos n\u00fameros estava acertando por partida.</p>\n<p>Sendo um bom netinho que voc\u00ea \u00e9, voc\u00ea desisdiu criar um programa que ajudasse sua vovozinha.</p>\n<h2 id=\"a\u00e7\u00e3o\">A\u00e7\u00e3o</h2>\n<p>Dado um vetor de tamanho 6 de elementos inteiros, verifique quantos elementos deste vetor est\u00e3o nesta matriz de elementos inteiros 4x4.</p>\n<p>1 9 27 23<br />\n34 20 37 47<br />\n30 87 55 69<br />\n13 60 99 66</p>\n<h3 id=\"entrada\">Entrada</h3>\n<ul>\n<li>Entrada de 6 numero inteiros</li>\n</ul>\n<h3 id=\"sa\u00edda\">Sa\u00edda</h3>\n<ul>\n<li>N\u00famero de vezes que os elementos do vetor e repetem na matriz 4x4.</li>\n</ul>\n<h2 id=\"exemplos\">Exemplos</h2>\n<pre><code>&gt;&gt;&gt;&gt;&gt;&gt;&gt;&gt;\n55 30 2 974 79 23\n========\n3\n&lt;&lt;&lt;&lt;&lt;&lt;&lt;&lt;\n\n&gt;&gt;&gt;&gt;&gt;&gt;&gt;&gt;\n2 7 88 31 19 40\n========\n0\n&lt;&lt;&lt;&lt;&lt;&lt;&lt;&lt;\n\n&gt;&gt;&gt;&gt;&gt;&gt;&gt;&gt;\n47 20 23 27 9 1\n========\n6\n&lt;&lt;&lt;&lt;&lt;&lt;&lt;&lt;</code></pre>\n<h1 id=\"section\"></h1>\n</body>\n</html>\n",
  "executionFiles": [
    {
      "name": "vpl_evaluate.cases",
      "contents": "case=00\ninput=55 30 2 974 79 23\noutput=\"3\n\"\ngrade reduction=100%\n\n\ncase=01\ninput=2 7 88 31 19 40\noutput=\"0\n\"\ngrade reduction=100%\n\n\ncase=02\ninput=47 20 23 27 9 1\noutput=\"6\n\"\ngrade reduction=100%\n\n\ncase=03\ninput=1 7 5 3 4 8\n1 2 3 4\n5 6 7 8\n9 10 11 12\n13 14 15 16\noutput=\"6\n\"\ngrade reduction=100%\n\n\ncase=04\ninput=21 48 9 12 7 1\n11 17 21 45\n33 55 22 15\n12 3 18 36\n49 51 7 80\noutput=\"3\n\"\ngrade reduction=100%\n"
    },
    {
      "name": "solver.c.txt",
      "contents": "#include <stdio.h>\n\nvoid bingo(int vet[6], int mat[4][4]){\n\n    int cont = 0;\n\n    for(int k = 0; k < 6; k++)\n        for(int i = 0; i < 4; i++)\n            for(int j = 0; j < 4; j++)\n                if(vet[k] == mat[i][j])\n                    cont++;\n\n    printf(\"%d\\n\", cont);\n}\n\nint main(){\n    int vet[6];\n        for(int i=0;i < 6;i++)\n            scanf(\"%d\", &vet[i]);\n    int mat[4][4] = {{1, 9, 27, 23}, {34, 20, 37, 47}, {30, 87, 55, 69}, {13, 60, 99, 66}};\n        for(int i =0; i < 4;i++)\n            for(int j=0;j < 4;j++)\n                scanf(\"%d\", &mat[i][j]);\n\n    bingo(vet,mat);\n}"
    }
  ],
  "requiredFile": null
}