{
    "title": "@101 L2 - Mostrar cartas",
    "description": "<!DOCTYPE html>\n<html xmlns=\"http://www.w3.org/1999/xhtml\" lang=\"\" xml:lang=\"\">\n<head>\n  <meta charset=\"utf-8\" />\n  <meta name=\"generator\" content=\"pandoc\" />\n  <meta name=\"viewport\" content=\"width=device-width, initial-scale=1.0, user-scalable=yes\" />\n  <title>@101 L2 - Mostrar cartas</title>\n  <style>\n    code{white-space: pre-wrap;}\n    span.smallcaps{font-variant: small-caps;}\n    div.columns{display: flex; gap: min(4vw, 1.5em);}\n    div.column{flex: auto; overflow-x: auto;}\n    div.hanging-indent{margin-left: 1.5em; text-indent: -1.5em;}\n    ul.task-list{list-style: none;}\n    ul.task-list li input[type=\"checkbox\"] {\n      width: 0.8em;\n      margin: 0 0.8em 0.2em -1.6em;\n      vertical-align: middle;\n    }\n  </style>\n  <link rel=\"stylesheet\" href=\"/tmp/tmpz_s0dj0m.css\" />\n  <!--[if lt IE 9]>\n    <script src=\"//cdnjs.cloudflare.com/ajax/libs/html5shiv/3.7.3/html5shiv-printshiv.min.js\"></script>\n  <![endif]-->\n</head>\n<body>\n<h1 id=\"l2---mostrar-cartas\"><span class=\"citation\"\ndata-cites=\"101\">@101</span> L2 - Mostrar cartas</h1>\n<p>Veja a vers\u00e3o online: <a\nhref=\"https://github.com/qxcodefup/arcade/blob/master/base/101/Readme.md\">aqui.</a>\n### Imprimir vetor formatado</p>\n<figure>\n<img\nsrc=\"https://raw.githubusercontent.com/qxcodefup/arcade/master/base/101/cover.jpg\"\nalt=\"_\" />\n<figcaption aria-hidden=\"true\">_</figcaption>\n</figure>\n<h2 id=\"a\u00e7\u00e3o\">A\u00e7\u00e3o</h2>\n<p>Leia um vetor contendo uma m\u00e3o de cartas e mostre as cartas para o\nusu\u00e1rio.</p>\n<p>As cartas est\u00e3o codificadas da seguinte forma. O 1 vale A, os valores\n11, 12 e 13 valem respectivamente J, Q e K.</p>\n<h2 id=\"entrada\">Entrada</h2>\n<ul>\n<li><p>1\u00aa linha: \u2018N\u2019 quantidade de cartas na m\u00e3o</p></li>\n<li><p>2\u00aa linha: \u2018N\u2019 valores representando as cartas do usu\u00e1rio. ##\nSa\u00edda</p></li>\n<li><p>Vetor formatado entre [ ], separados por \u2019 , \u2019.</p></li>\n</ul>\n<h2 id=\"exemplos\">Exemplos</h2>\n<p>```txt &gt;&gt;&gt;&gt;&gt;&gt;&gt;&gt; 0 ======== []\n&lt;&lt;&lt;&lt;&lt;&lt;&lt;&lt;</p>\n<blockquote>\n<blockquote>\n<blockquote>\n<blockquote>\n<blockquote>\n<blockquote>\n<blockquote>\n<blockquote>\n<p>13 1 2 3 4 5 6 7 8 9 10 11 12 13 ======== [A, 2, 3, 4, 5, 6, 7, 8, 9,\n10, J, Q, K] &lt;&lt;&lt;&lt;&lt;&lt;&lt;&lt;</p>\n</blockquote>\n</blockquote>\n</blockquote>\n</blockquote>\n</blockquote>\n</blockquote>\n</blockquote>\n</blockquote>\n<blockquote>\n<blockquote>\n<blockquote>\n<blockquote>\n<blockquote>\n<blockquote>\n<blockquote>\n<blockquote>\n<p>4 1 1 3 13 ======== [A, A, 3, K] &lt;&lt;&lt;&lt;&lt;&lt;&lt;&lt;</p>\n</blockquote>\n</blockquote>\n</blockquote>\n</blockquote>\n</blockquote>\n</blockquote>\n</blockquote>\n</blockquote>\n<blockquote>\n<blockquote>\n<blockquote>\n<blockquote>\n<blockquote>\n<blockquote>\n<blockquote>\n<blockquote>\n<p>6 1 12 13 1 1 10 ======== [A, Q, K, A, A, 10]\n&lt;&lt;&lt;&lt;&lt;&lt;&lt;&lt;</p>\n</blockquote>\n</blockquote>\n</blockquote>\n</blockquote>\n</blockquote>\n</blockquote>\n</blockquote>\n</blockquote>\n<blockquote>\n<blockquote>\n<blockquote>\n<blockquote>\n<blockquote>\n<blockquote>\n<blockquote>\n<blockquote>\n<p>6 10 10 2 2 11 1 ======== [10, 10, 2, 2, J, A]\n&lt;&lt;&lt;&lt;&lt;&lt;&lt;&lt; ```txt</p>\n</blockquote>\n</blockquote>\n</blockquote>\n</blockquote>\n</blockquote>\n</blockquote>\n</blockquote>\n</blockquote>\n</body>\n</html>\n",
    "upload": [
        {
            "name": "vpl_evaluate.cases",
            "contents": ">>>>>>>> None%\n0\n========\n[]\n<<<<<<<<\n\n>>>>>>>> None%\n13\n1 2 3 4 5 6 7 8 9 10 11 12 13\n========\n[A, 2, 3, 4, 5, 6, 7, 8, 9, 10, J, Q, K]\n<<<<<<<<\n\n>>>>>>>> None%\n4\n1 1 3 13\n========\n[A, A, 3, K]\n<<<<<<<<\n\n>>>>>>>> None%\n6\n1 12 13 1 1 10\n========\n[A, Q, K, A, A, 10]\n<<<<<<<<\n\n>>>>>>>> None%\n6\n10 10 2 2 11 1\n========\n[10, 10, 2, 2, J, A]\n<<<<<<<<\n",
            "encoding": 0
        }
    ],
    "keep": [],
    "required": []
}
