{
    "title": "@pares: Calculando soma",
    "description": "# Calculando soma\n\n![_](https://raw.githubusercontent.com/qxcodefup/arcade/master/base/pares/cover.jpg)\n\n## Contexto\n\n- Crian\u00e7a: Pai, a tia falou que na arca de No\u00e9 os animais entravam aos pares. O que \u00e9 pares, papai?\n- Pai: Pares s\u00e3o n\u00fameros que formam um casalzinho. Tipo 2 passarinhos. Mas tamb\u00e9m vale para v\u00e1rios pares, como 4, 6, 8, 10, etc.\n- Crian\u00e7a: Papai, e se n\u00e3o tiver nenhum passarinho pra botar na arca, 0 \u00e9 par?\n\nEssa pergunta nos leva a pensar nos n\u00fameros pares e como eles se comportam em diferentes intervalos de valores. Vamos explorar isso somando todos os n\u00fameros pares entre dois n\u00fameros inteiros.\n\nDado dois n\u00fameros inteiros **A** e **B**, some todos os n\u00fameros inteiros pares que est\u00e3o entre **A** e **B**, inclusive **A** e **B**.\n\n### Entrada\n\n- Dois n\u00fameros inteiros **A** e **B**, sendo **B** maior ou igual a **A**.\n\n### Sa\u00edda\n\n- A soma de todos os n\u00fameros pares entre **A** e **B**, inclusive **A** e **B**.\n- Se **A** for maior que **B**, imprima **\"invalido\"**.\n\n## Testes\n\n```py\n>>>>>>>> INSERT\n1\n10\n======== EXPECT\n30\n<<<<<<<< FINISH\n```\n\n```py\n>>>>>>>> INSERT\n1\n5\n======== EXPECT\n6\n<<<<<<<< FINISH\n```\n\n```py\n>>>>>>>> INSERT\n5\n1\n======== EXPECT\ninvalido\n<<<<<<<< FINISH\n```\n\n```py\n>>>>>>>> INSERT\n6\n6\n======== EXPECT\n6\n<<<<<<<< FINISH\n```\n\n## Dicas\n\n- Zero \u00e9 par?\n\nDescubra mais em [LINK](http://www.profcardy.com/cardicas/tirateima.php?id=1).\n",
    "upload": [
        {
            "name": "vpl_evaluate.cases",
            "contents": ">>>>>>>> INSERT\n1\n10\n======== EXPECT\n30\n<<<<<<<< FINISH\n\n\n>>>>>>>> INSERT\n1\n5\n======== EXPECT\n6\n<<<<<<<< FINISH\n\n\n>>>>>>>> INSERT\n5\n1\n======== EXPECT\ninvalido\n<<<<<<<< FINISH\n\n\n>>>>>>>> INSERT\n6\n6\n======== EXPECT\n6\n<<<<<<<< FINISH\n\n\n>>>>>>>> INSERT 05\n10\n20\n======== EXPECT\n90\n<<<<<<<< FINISH\n\n\n>>>>>>>> INSERT 06\n1\n7\n======== EXPECT\n12\n<<<<<<<< FINISH\n\n\n>>>>>>>> INSERT 07\n8\n8\n======== EXPECT\n8\n<<<<<<<< FINISH\n\n",
            "type": "hide"
        }
    ],
    "draft": {}
}
