{
    "title": "@idosa: Mulher mais idosa",
    "description": "# Mulher mais idosa\n\n![_](https://raw.githubusercontent.com/qxcodefup/arcade/master/base/idosa/cover.jpg)\n\n## A\u00e7\u00e3o\n\nLeia um grupo de pessoas e informe o nome da mulher mais idosa do grupo.\n\nCada pessoa tem nome(string at\u00e9 20 char, sem whitespace), idade(int) e sexo(char 'm' ou 'f').\n\n### Entrada\n\n- 1a linha: o n\u00famero de pessoas, seguido por uma pessoa por linha.\n\n## Sa\u00edda\n\n- O nome da mulher mais idosa, ou 'nao ha mulher' se n\u00e3o houverem mulheres no grupo.\n\n## Orienta\u00e7\u00f5es\n\nAntes e fazer a busca pela mulher mais idosa, voc\u00ea deve ler os dados e armazen\u00e1-los em um vetor de struct.\n\n## Exemplos\n\n``` py\n>>>>>>>> INSERT 01\n2\nana 80 f\njoao 43 m\n======== EXPECT\nana\n<<<<<<<< FINISH\n```\n\n```py\n>>>>>>>> INSERT 02\n2\njose 80 m\njoao 43 m\n======== EXPECT\nnao tem mulher\n<<<<<<<< FINISH\n```\n\n```py\n>>>>>>>> INSERT 03\n3\njoao 43 m\nana 80 f\nmelissa 34 f\n======== EXPECT\nana\n<<<<<<<< FINISH\n```\n\n```py\n>>>>>>>> INSERT 04\n3\njoao 88 m\nana 80 f\nmelissa 84 f\n======== EXPECT\nmelissa\n<<<<<<<< FINISH\n```\n",
    "upload": [
        {
            "name": "vpl_evaluate.cases",
            "contents": ">>>>>>>> INSERT 01\n2\nana 80 f\njoao 43 m\n======== EXPECT\nana\n<<<<<<<< FINISH\n\n\n>>>>>>>> INSERT 02\n2\njose 80 m\njoao 43 m\n======== EXPECT\nnao tem mulher\n<<<<<<<< FINISH\n\n\n>>>>>>>> INSERT 03\n3\njoao 43 m\nana 80 f\nmelissa 34 f\n======== EXPECT\nana\n<<<<<<<< FINISH\n\n\n>>>>>>>> INSERT 04\n3\njoao 88 m\nana 80 f\nmelissa 84 f\n======== EXPECT\nmelissa\n<<<<<<<< FINISH\n\n\n>>>>>>>> INSERT 05\n3\njoao 88 m\nferrim 80 m\nmelios 84 m\n======== EXPECT\nnao tem mulher\n<<<<<<<< FINISH\n\n\n>>>>>>>> INSERT 06\n7\nmaria 11 f\njoao 43 m\nfrancisco 12 m\nmeire 71 f\nsergio 14 m\nstrange 81 m\nmogli 45 m\n======== EXPECT\nmeire\n<<<<<<<< FINISH\n\n\n>>>>>>>> INSERT 07\n6\nmaria 11 f\njoao 43 m\nfrancisco 12 m\nmeire 71 f\nstrange 81 m\nsergio 101 m\n======== EXPECT\nmeire\n<<<<<<<< FINISH\n\n\n>>>>>>>> INSERT 08\n5\nmaria 99 f\nstrange 81 m\njoao 43 m\nmeire 71 f\nsergio 14 m\n======== EXPECT\nmaria\n<<<<<<<< FINISH\n\n\n>>>>>>>> INSERT 09\n7\nmario 80 m\njoao 43 m\nfrancisco 12 m\nmeire 73 f\nsergio 72 f\nstrange 81 m\nmogli 45 m\n======== EXPECT\nmeire\n<<<<<<<< FINISH\n\n",
            "type": "hide"
        }
    ],
    "draft": {}
}
